django_jsonfallback-2.1.2.dist-info/METADATA
django_jsonfallback-2.1.2.dist-info/RECORD
django_jsonfallback-2.1.2.dist-info/WHEEL
django_jsonfallback-2.1.2.dist-info/top_level.txt
jsonfallback/__init__.py
jsonfallback/fields.py
jsonfallback/functions.py
