Metadata-Version: 2.1
Name: django-jsonfallback
Version: 2.1.2
Summary: JSONField from django.contrib.postgres, but with a fallback to TextField
Home-page: https://github.com/raphaelm/django-jsonfallback
Author: Raphael Michel
Author-email: mail@raphaelmichel.de
License: Apache License 2.0
Keywords: json database models
Platform: UNKNOWN
Classifier: Intended Audience :: Developers
Classifier: Intended Audience :: Other Audience
Classifier: License :: OSI Approved :: Apache Software License
Classifier: Programming Language :: Python :: 3.4
Classifier: Programming Language :: Python :: 3.5
Classifier: Programming Language :: Python :: 3.6
Classifier: Framework :: Django :: 2.1
Requires-Dist: django-mysql
